{"01_speckle.png54873":{"filename":"01_speckle.png","size":54873,"regions":[{"shape_attributes":{"name":"polygon","all_points_x":[139,144,144,65,60],"all_points_y":[32,34,36,129,126]},"region_attributes":{}}],"file_attributes":{}},"02_speckle.png54809":{"filename":"02_speckle.png","size":54809,"regions":[{"shape_attributes":{"name":"polygon","all_points_x":[164,58,64,166],"all_points_y":[28,144,146,37]},"region_attributes":{}}],"file_attributes":{}},"03_speckle.png46899":{"filename":"03_speckle.png","size":46899,"regions":[{"shape_attributes":{"name":"polygon","all_points_x":[159,85,90,160],"all_points_y":[29,119,121,32]},"region_attributes":{}}],"file_attributes":{}},"04_speckle.png47121":{"filename":"04_speckle.png","size":47121,"regions":[{"shape_attributes":{"name":"polygon","all_points_x":[90,96,174,170],"all_points_y":[123,124,30,24]},"region_attributes":{}}],"file_attributes":{}},"05_speckle.png47082":{"filename":"05_speckle.png","size":47082,"regions":[{"shape_attributes":{"name":"polygon","all_points_x":[99,104,162,160,155],"all_points_y":[108,110,41,35,36]},"region_attributes":{}}],"file_attributes":{}},"06_speckle.png46883":{"filename":"06_speckle.png","size":46883,"regions":[{"shape_attributes":{"name":"polygon","all_points_x":[112,118,180,178,173],"all_points_y":[122,123,50,43,48]},"region_attributes":{}}],"file_attributes":{}},"07_speckle.png46873":{"filename":"07_speckle.png","size":46873,"regions":[{"shape_attributes":{"name":"polygon","all_points_x":[57,63,125,118],"all_points_y":[100,100,24,24]},"region_attributes":{}}],"file_attributes":{}},"08_speckle.png47090":{"filename":"08_speckle.png","size":47090,"regions":[{"shape_attributes":{"name":"polygon","all_points_x":[31,37,129,122],"all_points_y":[126,129,28,26]},"region_attributes":{}}],"file_attributes":{}},"09_speckle.png47195":{"filename":"09_speckle.png","size":47195,"regions":[{"shape_attributes":{"name":"polygon","all_points_x":[22,27,122,119,116],"all_points_y":[127,130,20,14,16]},"region_attributes":{}}],"file_attributes":{}},"10_speckle.png47242":{"filename":"10_speckle.png","size":47242,"regions":[{"shape_attributes":{"name":"polygon","all_points_x":[6,13,133,121],"all_points_y":[126,130,5,5]},"region_attributes":{}}],"file_attributes":{}},"11_speckle.png47192":{"filename":"11_speckle.png","size":47192,"regions":[{"shape_attributes":{"name":"polygon","all_points_x":[117,134,2,2],"all_points_y":[5,6,142,124]},"region_attributes":{}}],"file_attributes":{}},"12_speckle.png47085":{"filename":"12_speckle.png","size":47085,"regions":[{"shape_attributes":{"name":"polygon","all_points_x":[108,132,0,0],"all_points_y":[4,4,144,123]},"region_attributes":{}}],"file_attributes":{}},"13_speckle.png46891":{"filename":"13_speckle.png","size":46891,"regions":[{"shape_attributes":{"name":"polygon","all_points_x":[120,160,2,1],"all_points_y":[3,3,180,143]},"region_attributes":{}}],"file_attributes":{}},"14_speckle.png46118":{"filename":"14_speckle.png","size":46118,"regions":[{"shape_attributes":{"name":"polygon","all_points_x":[126,180,20,0,1],"all_points_y":[1,2,180,180,136]},"region_attributes":{}}],"file_attributes":{}},"15_speckle.png43440":{"filename":"15_speckle.png","size":43440,"regions":[{"shape_attributes":{"name":"polygon","all_points_x":[102,193,43,0,1],"all_points_y":[2,2,181,181,111]},"region_attributes":{}}],"file_attributes":{}},"16_speckle.png45089":{"filename":"16_speckle.png","size":45089,"regions":[{"shape_attributes":{"name":"polygon","all_points_x":[90,170,1,1],"all_points_y":[1,1,165,100]},"region_attributes":{}}],"file_attributes":{}},"17_speckle.png48190":{"filename":"17_speckle.png","size":48190,"regions":[{"shape_attributes":{"name":"polygon","all_points_x":[124,126,80,76],"all_points_y":[99,102,157,155]},"region_attributes":{}}],"file_attributes":{}},"18_speckle.png48284":{"filename":"18_speckle.png","size":48284,"regions":[{"shape_attributes":{"name":"polygon","all_points_x":[74,74,79,143,143,138],"all_points_y":[170,174,173,108,99,101]},"region_attributes":{}}],"file_attributes":{}},"19_speckle.png42864":{"filename":"19_speckle.png","size":42864,"regions":[{"shape_attributes":{"name":"polygon","all_points_x":[56,65,122,122],"all_points_y":[171,170,107,96]},"region_attributes":{}}],"file_attributes":{}},"20_speckle.png42956":{"filename":"20_speckle.png","size":42956,"regions":[{"shape_attributes":{"name":"polygon","all_points_x":[37,51,122,123,118],"all_points_y":[183,183,102,95,95]},"region_attributes":{}}],"file_attributes":{}},"21_speckle.png42831":{"filename":"21_speckle.png","size":42831,"regions":[{"shape_attributes":{"name":"polygon","all_points_x":[32,50,122,122,117],"all_points_y":[190,190,105,97,100]},"region_attributes":{}}],"file_attributes":{}},"22_speckle.png42488":{"filename":"22_speckle.png","size":42488,"regions":[{"shape_attributes":{"name":"polygon","all_points_x":[18,46,120,121],"all_points_y":[216,217,121,98]},"region_attributes":{}}],"file_attributes":{}},"23_speckle.png42423":{"filename":"23_speckle.png","size":42423,"regions":[{"shape_attributes":{"name":"polygon","all_points_x":[37,118,119,70],"all_points_y":[223,118,153,223]},"region_attributes":{}}],"file_attributes":{}},"24_speckle.png41998":{"filename":"24_speckle.png","size":41998,"regions":[{"shape_attributes":{"name":"polygon","all_points_x":[38,80,122,121],"all_points_y":[224,224,174,126]},"region_attributes":{}}],"file_attributes":{}},"25_speckle.png41641":{"filename":"25_speckle.png","size":41641,"regions":[{"shape_attributes":{"name":"polygon","all_points_x":[118,26,92,120],"all_points_y":[115,224,223,190]},"region_attributes":{}}],"file_attributes":{}}}